{
    "ParkAgent": {
        "checkpoints": [
            {
                "steps": 27157,
                "file_path": "results\\C30\\ParkAgent\\ParkAgent-27157.onnx",
                "reward": -991.0434504747391,
                "creation_time": 1652478696.158806,
                "auxillary_file_paths": [
                    "results\\C30\\ParkAgent\\ParkAgent-27157.pt"
                ]
            }
        ],
        "final_checkpoint": {
            "steps": 27157,
            "file_path": "results\\C30\\ParkAgent.onnx",
            "reward": -991.0434504747391,
            "creation_time": 1652478696.158806,
            "auxillary_file_paths": [
                "results\\C30\\ParkAgent\\ParkAgent-27157.pt"
            ]
        }
    },
    "metadata": {
        "stats_format_version": "0.3.0",
        "mlagents_version": "0.28.0",
        "torch_version": "1.7.1+cu110"
    }
}